reqpi/__init__.py
reqpi/server.py
reqpi/gethash.py
reqpi/__main__.py
reqpi/plugin.py
reqpi/_version.py
reqpi/db/model.py
reqpi/db/__init__.py
reqpi/robot/__init__.py
reqpi/robot/locator.py
reqpi/robot/hash.py
reqpi/human/upload.py
reqpi/human/__init__.py
reqpi/human/requirements.py
reqpi/human/grabber.py
reqpi/test/__init__.py
reqpi/test/travis.py
reqpi/test/integration.py
reqpi/test/test_gethash.py
reqpi/test/test_plugin.py
reqpi/test/test_db/__init__.py
reqpi/test/test_db/test_model.py
reqpi/test/test_robot/test_hash.py
reqpi/test/test_robot/__init__.py
reqpi/test/test_robot/test_locator.py
twisted/plugins/reqpi.py
reqpi-0.0.1.dist-info/metadata.json
reqpi-0.0.1.dist-info/METADATA
reqpi-0.0.1.dist-info/WHEEL
reqpi-0.0.1.dist-info/DESCRIPTION.rst
reqpi-0.0.1.dist-info/RECORD
reqpi-0.0.1.dist-info/top_level.txt
