Metadata-Version: 2.0
Name: reqpi
Version: 0.0.1
Summary: Requirements-only PyPI-compatible server
Home-page: https://github.com/square/reqpi
Author: Square, Inc.
Author-email: moshez@squareup.com
License: Apache
Platform: UNKNOWN
Requires-Dist: mainland
Requires-Dist: Twisted
